README.md
license.txt
setup.py
crawler_telefone/__init__.py
crawler_telefone/main.py
crawler_telefone_PT_BR_version.egg-info/PKG-INFO
crawler_telefone_PT_BR_version.egg-info/SOURCES.txt
crawler_telefone_PT_BR_version.egg-info/dependency_links.txt
crawler_telefone_PT_BR_version.egg-info/top_level.txt