Metadata-Version: 2.1
Name: crawler-telefone-PT-BR-version
Version: 1.0
Summary: Crawler para pegar telefones em sites. Totalmente amador e apenas de TESTE.
Author: Gabriel
Author-email: gabrielmarquessant062@gmail.com
Keywords: crawler,telefone
License-File: license.txt
